opstats/__init__.py
opstats/covariance.py
opstats/extended.py
opstats/moments.py
opstats/tests/__init__.py
opstats/tests/base.py
opstats/tests/test_covariance.py
opstats/tests/test_covariance_agg.py
opstats/tests/test_extended.py
opstats/tests/test_extended_agg.py
opstats/tests/test_moment_agg.py
opstats/tests/test_moments.py
opstats-1.2.0.dist-info/LICENSE
opstats-1.2.0.dist-info/METADATA
opstats-1.2.0.dist-info/WHEEL
opstats-1.2.0.dist-info/top_level.txt
opstats-1.2.0.dist-info/RECORD
