Metadata-Version: 2.1
Name: opstats
Version: 1.2.0
Summary: Online parallel statistics calculator.
Author-email: arkershaw@users.noreply.github.com
License: GNU GENERAL PUBLIC LICENSE
Project-URL: Homepage, https://github.com/arkershaw/opstats
Project-URL: Issues, https://github.com/arkershaw/opstats/issues
Keywords: statistics,parallel,streaming
Classifier: Development Status :: 4 - Beta
Classifier: Intended Audience :: Developers
Classifier: Intended Audience :: Science/Research
Classifier: License :: OSI Approved :: GNU General Public License v3 (GPLv3)
Classifier: Natural Language :: English
Classifier: Operating System :: OS Independent
Classifier: Programming Language :: Python :: 3
Classifier: Topic :: Scientific/Engineering :: Mathematics
Classifier: Typing :: Typed
Requires-Python: >=3.6
License-File: LICENSE
Provides-Extra: extended
Requires-Dist: hyperloglog ; extra == 'extended'
Requires-Dist: tdigest ; extra == 'extended'
